{
  "date": "2026-03-13",
  "timestamp": "2026-03-13T04:14:33Z",
  "summary": "The Hormuz-driven oil shock and February's -92,000 payroll print have collided into a stagflation threat, leaving the Fed trapped between holding against energy inflation and easing into a weakening labor market. The 10-year Treasury yield climbed to 4.19% on March 11 as a market-driven inflationary risk premium \u2014 not Fed hikes \u2014 pushed long rates higher, weighing on bond duration and equity valuations simultaneously.",
  "scores": {
    "gold": {
      "score": 52.6,
      "label": "Neutral"
    },
    "stocks": {
      "score": 43.2,
      "label": "Fear"
    },
    "crypto": {
      "score": 51.2,
      "label": "Neutral"
    },
    "bonds": {
      "score": 45.2,
      "label": "Fear"
    },
    "sentiment": {
      "score": 48.0,
      "label": "Neutral"
    }
  }
}